montafons/__init__.py
montafons/montafons.py
montafons-1.0.0.dist-info/METADATA
montafons-1.0.0.dist-info/WHEEL
montafons-1.0.0.dist-info/entry_points.txt
montafons-1.0.0.dist-info/RECORD
