Metadata-Version: 2.4
Name: montafons
Version: 1.0.0
Summary: Python library to generate an image collage from other images. I mainly use it to generate horizontal wallpapers from multiple vertical images, but feel free to use it for any other purpuse.
Project-URL: Homepage, https://github.com/lluises/montafons
Project-URL: Issues, https://github.com/lluises/montafons/issues
Author-email: LluísE <lluise@github.com>
Classifier: License :: OSI Approved :: Mozilla Public License 2.0 (MPL 2.0)
Classifier: Operating System :: OS Independent
Classifier: Programming Language :: Python :: 3
Requires-Python: >=3.6
Requires-Dist: pillow>=11.0.0
